autolocalise/__init__.py
autolocalise/_version.py
autolocalise/cache.py
autolocalise/exceptions.py
autolocalise/translator.py
autolocalise-0.1.3.dist-info/licenses/LICENSE
tests/__init__.py
tests/test_cache_functionality.py
tests/test_template_support.py
tests/test_translation_api.py
tests/test_translator_core.py
autolocalise-0.1.3.dist-info/METADATA
autolocalise-0.1.3.dist-info/WHEEL
autolocalise-0.1.3.dist-info/top_level.txt
autolocalise-0.1.3.dist-info/RECORD
